{
    "DBSnapshots": [
        {
            "AllocatedStorage": 100,
            "AvailabilityZone": "ap-northeast-1a",
            "DBInstanceIdentifier": "noin-production",
            "DBSnapshotArn": "arn:aws:rds:ap-northeast-1:416817624313:snapshot:before-noin-lotto-grant-point-2019-01-07",
            "DBSnapshotIdentifier": "before-noin-lotto-grant-point-2019-01-07",
            "DbiResourceId": "db-HVCA4EWWHHTDSCEVLZMXCE4RCE",
            "Encrypted": true,
            "Engine": "mysql",
            "EngineVersion": "5.6.40",
            "IAMDatabaseAuthenticationEnabled": false,
            "InstanceCreateTime": "2017-10-05T06:08:16.614000+00:00",
            "KmsKeyId": "arn:aws:kms:ap-northeast-1:416817624313:key/f70c542e-295f-4e09-a995-c208de9af8e9",
            "LicenseModel": "general-public-license",
            "MasterUsername": "noin_backend",
            "OptionGroupName": "default:mysql-5-6",
            "PercentProgress": 100,
            "Port": 3306,
            "ProcessorFeatures": [],
            "SnapshotCreateTime": "2019-01-06T15:12:36.608000+00:00",
            "SnapshotType": "manual",
            "Status": "available",
            "StorageType": "gp2",
            "VpcId": "vpc-b0eae7d4"
        },
        {
            "AllocatedStorage": 100,
            "AvailabilityZone": "ap-northeast-1c",
            "DBInstanceIdentifier": "category-test2",
            "DBSnapshotArn": "arn:aws:rds:ap-northeast-1:416817624313:snapshot:category-test2-final-snapshot",
            "DBSnapshotIdentifier": "category-test2-final-snapshot",
            "DbiResourceId": "db-L2OQWJ3ZXVSEBIAYQIDWRF5V7U",
            "Encrypted": true,
            "Engine": "mysql",
            "EngineVersion": "5.6.43",
            "IAMDatabaseAuthenticationEnabled": false,
            "InstanceCreateTime": "2019-11-27T01:19:17.306000+00:00",
            "KmsKeyId": "arn:aws:kms:ap-northeast-1:416817624313:key/f70c542e-295f-4e09-a995-c208de9af8e9",
            "LicenseModel": "general-public-license",
            "MasterUsername": "noin_backend",
            "OptionGroupName": "default:mysql-5-6",
            "PercentProgress": 100,
            "Port": 3306,
            "ProcessorFeatures": [],
            "SnapshotCreateTime": "2019-12-02T01:51:30.235000+00:00",
            "SnapshotType": "manual",
            "Status": "available",
            "StorageType": "gp2",
            "VpcId": "vpc-4ec1e72a"
        },
        {
            "AllocatedStorage": 100,
            "AvailabilityZone": "ap-northeast-1c",
            "DBInstanceIdentifier": "category-test3",
            "DBSnapshotArn": "arn:aws:rds:ap-northeast-1:416817624313:snapshot:category-test3-final-snapshot",
            "DBSnapshotIdentifier": "category-test3-final-snapshot",
            "DbiResourceId": "db-7ECRFR2DXMEAHJGHBE2AEM6JPM",
            "Encrypted": true,
            "Engine": "mysql",
            "EngineVersion": "5.6.43",
            "IAMDatabaseAuthenticationEnabled": false,
            "InstanceCreateTime": "2019-11-28T14:39:04.101000+00:00",
            "KmsKeyId": "arn:aws:kms:ap-northeast-1:416817624313:key/f70c542e-295f-4e09-a995-c208de9af8e9",
            "LicenseModel": "general-public-license",
            "MasterUsername": "noin_backend",
            "OptionGroupName": "default:mysql-5-6",
            "PercentProgress": 100,
            "Port": 3306,
            "ProcessorFeatures": [],
            "SnapshotCreateTime": "2019-12-02T01:51:51.316000+00:00",
            "SnapshotType": "manual",
            "Status": "available",
            "StorageType": "gp2",
            "VpcId": "vpc-4ec1e72a"
        },
        {
            "AllocatedStorage": 10,
            "AvailabilityZone": "ap-northeast-1a",
            "DBInstanceIdentifier": "gmo-test",
            "DBSnapshotArn": "arn:aws:rds:ap-northeast-1:416817624313:snapshot:gmo-test-final-snapshot-2018-08-13-19-20",
            "DBSnapshotIdentifier": "gmo-test-final-snapshot-2018-08-13-19-20",
            "DbiResourceId": "db-O7YY7JXV2OYJ72GRGZ4CFRPQUM",
            "Encrypted": false,
            "Engine": "mysql",
            "EngineVersion": "5.6.35",
            "IAMDatabaseAuthenticationEnabled": false,
            "InstanceCreateTime": "2018-08-07T03:33:41.546000+00:00",
            "LicenseModel": "general-public-license",
            "MasterUsername": "root",
            "OptionGroupName": "default:mysql-5-6",
            "PercentProgress": 100,
            "Port": 3306,
            "ProcessorFeatures": [],
            "SnapshotCreateTime": "2018-08-13T10:34:31.082000+00:00",
            "SnapshotType": "manual",
            "Status": "available",
            "StorageType": "gp2",
            "VpcId": "vpc-4ec1e72a"
        },
        {
            "AllocatedStorage": 100,
            "AvailabilityZone": "ap-northeast-1a",
            "DBInstanceIdentifier": "noin-corp",
            "DBSnapshotArn": "arn:aws:rds:ap-northeast-1:416817624313:snapshot:noin-corp-final-snapshot",
            "DBSnapshotIdentifier": "noin-corp-final-snapshot",
            "DbiResourceId": "db-ATCNJP4IXPOZOWMNOWITZW56IE",
            "Encrypted": true,
            "Engine": "mysql",
            "EngineVersion": "5.7.22",
            "IAMDatabaseAuthenticationEnabled": false,
            "InstanceCreateTime": "2019-06-04T07:43:16.757000+00:00",
            "KmsKeyId": "arn:aws:kms:ap-northeast-1:416817624313:key/f70c542e-295f-4e09-a995-c208de9af8e9",
            "LicenseModel": "general-public-license",
            "MasterUsername": "noin_corp",
            "OptionGroupName": "default:mysql-5-7",
            "PercentProgress": 100,
            "Port": 3306,
            "ProcessorFeatures": [],
            "SnapshotCreateTime": "2019-06-04T16:07:39.862000+00:00",
            "SnapshotType": "manual",
            "Status": "available",
            "StorageType": "gp2",
            "VpcId": "vpc-b0eae7d4"
        },
        {
            "AllocatedStorage": 100,
            "AvailabilityZone": "ap-northeast-1c",
            "DBInstanceIdentifier": "noin-production-20190617",
            "DBSnapshotArn": "arn:aws:rds:ap-northeast-1:416817624313:snapshot:noin-production-20190617-201906240408",
            "DBSnapshotIdentifier": "noin-production-20190617-201906240408",
            "DbiResourceId": "db-ONZWTN7HWO2DX26K2OZNB7VMC4",
            "Encrypted": true,
            "Engine": "mysql",
            "EngineVersion": "5.6.40",
            "IAMDatabaseAuthenticationEnabled": false,
            "InstanceCreateTime": "2019-06-16T21:54:51.778000+00:00",
            "KmsKeyId": "arn:aws:kms:ap-northeast-1:416817624313:key/f70c542e-295f-4e09-a995-c208de9af8e9",
            "LicenseModel": "general-public-license",
            "MasterUsername": "noin_backend",
            "OptionGroupName": "default:mysql-5-6",
            "PercentProgress": 100,
            "Port": 3306,
            "ProcessorFeatures": [],
            "SnapshotCreateTime": "2019-06-23T19:09:20.854000+00:00",
            "SnapshotType": "manual",
            "Status": "available",
            "StorageType": "gp2",
            "VpcId": "vpc-b0eae7d4"
        },
        {
            "AllocatedStorage": 100,
            "AvailabilityZone": "ap-northeast-1a",
            "DBInstanceIdentifier": "noin-production-2019-06-22test",
            "DBSnapshotArn": "arn:aws:rds:ap-northeast-1:416817624313:snapshot:noin-production-2019-06-22test-final-snapshot",
            "DBSnapshotIdentifier": "noin-production-2019-06-22test-final-snapshot",
            "DbiResourceId": "db-O7JNCHJUL63PPVCOXEQBU4UQ5U",
            "Encrypted": true,
            "Engine": "mysql",
            "EngineVersion": "5.6.43",
            "IAMDatabaseAuthenticationEnabled": false,
            "InstanceCreateTime": "2019-06-21T09:09:15.002000+00:00",
            "KmsKeyId": "arn:aws:kms:ap-northeast-1:416817624313:key/f70c542e-295f-4e09-a995-c208de9af8e9",
            "LicenseModel": "general-public-license",
            "MasterUsername": "noin_backend",
            "OptionGroupName": "default:mysql-5-6",
            "PercentProgress": 100,
            "Port": 3306,
            "ProcessorFeatures": [],
            "SnapshotCreateTime": "2019-06-24T05:30:50.380000+00:00",
            "SnapshotType": "manual",
            "Status": "available",
            "StorageType": "gp2",
            "VpcId": "vpc-b0eae7d4"
        },
        {
            "AllocatedStorage": 100,
            "AvailabilityZone": "ap-northeast-1c",
            "DBInstanceIdentifier": "noin-production",
            "DBSnapshotArn": "arn:aws:rds:ap-northeast-1:416817624313:snapshot:noin-production-201907170430",
            "DBSnapshotIdentifier": "noin-production-201907170430",
            "DbiResourceId": "db-ONZWTN7HWO2DX26K2OZNB7VMC4",
            "Encrypted": true,
            "Engine": "mysql",
            "EngineVersion": "5.6.43",
            "IAMDatabaseAuthenticationEnabled": false,
            "InstanceCreateTime": "2019-06-16T21:54:51.778000+00:00",
            "KmsKeyId": "arn:aws:kms:ap-northeast-1:416817624313:key/f70c542e-295f-4e09-a995-c208de9af8e9",
            "LicenseModel": "general-public-license",
            "MasterUsername": "noin_backend",
            "OptionGroupName": "default:mysql-5-6",
            "PercentProgress": 100,
            "Port": 3306,
            "ProcessorFeatures": [],
            "SnapshotCreateTime": "2019-07-16T19:31:08.716000+00:00",
            "SnapshotType": "manual",
            "Status": "available",
            "StorageType": "gp2",
            "VpcId": "vpc-b0eae7d4"
        },
        {
            "AllocatedStorage": 100,
            "AvailabilityZone": "ap-northeast-1c",
            "DBInstanceIdentifier": "noin-production",
            "DBSnapshotArn": "arn:aws:rds:ap-northeast-1:416817624313:snapshot:noin-production-201907190401",
            "DBSnapshotIdentifier": "noin-production-201907190401",
            "DbiResourceId": "db-ONZWTN7HWO2DX26K2OZNB7VMC4",
            "Encrypted": true,
            "Engine": "mysql",
            "EngineVersion": "5.6.43",
            "IAMDatabaseAuthenticationEnabled": false,
            "InstanceCreateTime": "2019-06-16T21:54:51.778000+00:00",
            "KmsKeyId": "arn:aws:kms:ap-northeast-1:416817624313:key/f70c542e-295f-4e09-a995-c208de9af8e9",
            "LicenseModel": "general-public-license",
            "MasterUsername": "noin_backend",
            "OptionGroupName": "default:mysql-5-6",
            "PercentProgress": 100,
            "Port": 3306,
            "ProcessorFeatures": [],
            "SnapshotCreateTime": "2019-07-18T19:01:41.695000+00:00",
            "SnapshotType": "manual",
            "Status": "available",
            "StorageType": "gp2",
            "VpcId": "vpc-b0eae7d4"
        },
        {
            "AllocatedStorage": 100,
            "AvailabilityZone": "ap-northeast-1c",
            "DBInstanceIdentifier": "noin-production",
            "DBSnapshotArn": "arn:aws:rds:ap-northeast-1:416817624313:snapshot:noin-production-201909260415",
            "DBSnapshotIdentifier": "noin-production-201909260415",
            "DbiResourceId": "db-ONZWTN7HWO2DX26K2OZNB7VMC4",
            "Encrypted": true,
            "Engine": "mysql",
            "EngineVersion": "5.6.43",
            "IAMDatabaseAuthenticationEnabled": false,
            "InstanceCreateTime": "2019-06-16T21:54:51.778000+00:00",
            "KmsKeyId": "arn:aws:kms:ap-northeast-1:416817624313:key/f70c542e-295f-4e09-a995-c208de9af8e9",
            "LicenseModel": "general-public-license",
            "MasterUsername": "noin_backend",
            "OptionGroupName": "default:mysql-5-6",
            "PercentProgress": 100,
            "Port": 3306,
            "ProcessorFeatures": [],
            "SnapshotCreateTime": "2019-09-25T19:15:24.707000+00:00",
            "SnapshotType": "manual",
            "Status": "available",
            "StorageType": "gp2",
            "VpcId": "vpc-b0eae7d4"
        },
        {
            "AllocatedStorage": 100,
            "AvailabilityZone": "ap-northeast-1c",
            "DBInstanceIdentifier": "noin-production",
            "DBSnapshotArn": "arn:aws:rds:ap-northeast-1:416817624313:snapshot:noin-production-201909260455",
            "DBSnapshotIdentifier": "noin-production-201909260455",
            "DbiResourceId": "db-ONZWTN7HWO2DX26K2OZNB7VMC4",
            "Encrypted": true,
            "Engine": "mysql",
            "EngineVersion": "5.6.43",
            "IAMDatabaseAuthenticationEnabled": false,
            "InstanceCreateTime": "2019-06-16T21:54:51.778000+00:00",
            "KmsKeyId": "arn:aws:kms:ap-northeast-1:416817624313:key/f70c542e-295f-4e09-a995-c208de9af8e9",
            "LicenseModel": "general-public-license",
            "MasterUsername": "noin_backend",
            "OptionGroupName": "default:mysql-5-6",
            "PercentProgress": 100,
            "Port": 3306,
            "ProcessorFeatures": [],
            "SnapshotCreateTime": "2019-09-25T19:57:06.124000+00:00",
            "SnapshotType": "manual",
            "Status": "available",
            "StorageType": "gp2",
            "VpcId": "vpc-b0eae7d4"
        },
        {
            "AllocatedStorage": 100,
            "AvailabilityZone": "ap-northeast-1c",
            "DBInstanceIdentifier": "noin-production",
            "DBSnapshotArn": "arn:aws:rds:ap-northeast-1:416817624313:snapshot:noin-production-201911280400",
            "DBSnapshotIdentifier": "noin-production-201911280400",
            "DbiResourceId": "db-ONZWTN7HWO2DX26K2OZNB7VMC4",
            "Encrypted": true,
            "Engine": "mysql",
            "EngineVersion": "5.6.43",
            "IAMDatabaseAuthenticationEnabled": false,
            "InstanceCreateTime": "2019-06-16T21:54:51.778000+00:00",
            "KmsKeyId": "arn:aws:kms:ap-northeast-1:416817624313:key/f70c542e-295f-4e09-a995-c208de9af8e9",
            "LicenseModel": "general-public-license",
            "MasterUsername": "noin_backend",
            "OptionGroupName": "default:mysql-5-6",
            "PercentProgress": 100,
            "Port": 3306,
            "ProcessorFeatures": [],
            "SnapshotCreateTime": "2019-11-27T19:03:16.625000+00:00",
            "SnapshotType": "manual",
            "Status": "available",
            "StorageType": "gp2",
            "VpcId": "vpc-b0eae7d4"
        },
        {
            "AllocatedStorage": 100,
            "AvailabilityZone": "ap-northeast-1c",
            "DBInstanceIdentifier": "noin-production",
            "DBSnapshotArn": "arn:aws:rds:ap-northeast-1:416817624313:snapshot:noin-production-final-snapshot",
            "DBSnapshotIdentifier": "noin-production-final-snapshot",
            "DbiResourceId": "db-HVCA4EWWHHTDSCEVLZMXCE4RCE",
            "Encrypted": true,
            "Engine": "mysql",
            "EngineVersion": "5.6.43",
            "IAMDatabaseAuthenticationEnabled": false,
            "InstanceCreateTime": "2017-10-05T06:08:16.614000+00:00",
            "KmsKeyId": "arn:aws:kms:ap-northeast-1:416817624313:key/f70c542e-295f-4e09-a995-c208de9af8e9",
            "LicenseModel": "general-public-license",
            "MasterUsername": "noin_backend",
            "OptionGroupName": "default:mysql-5-6",
            "PercentProgress": 100,
            "Port": 3306,
            "ProcessorFeatures": [],
            "SnapshotCreateTime": "2019-06-18T03:22:10.726000+00:00",
            "SnapshotType": "manual",
            "Status": "available",
            "StorageType": "gp2",
            "VpcId": "vpc-b0eae7d4"
        },
        {
            "AllocatedStorage": 100,
            "AvailabilityZone": "ap-northeast-1c",
            "DBInstanceIdentifier": "noin-production-rep-clone",
            "DBSnapshotArn": "arn:aws:rds:ap-northeast-1:416817624313:snapshot:noin-production-rep-clone-final-snapshot",
            "DBSnapshotIdentifier": "noin-production-rep-clone-final-snapshot",
            "DbiResourceId": "db-CKPZ3M5VCN2PXMGKZPB2MJTC2Q",
            "Encrypted": true,
            "Engine": "mysql",
            "EngineVersion": "5.6.43",
            "IAMDatabaseAuthenticationEnabled": false,
            "InstanceCreateTime": "2019-07-11T03:12:23.619000+00:00",
            "KmsKeyId": "arn:aws:kms:ap-northeast-1:416817624313:key/f70c542e-295f-4e09-a995-c208de9af8e9",
            "LicenseModel": "general-public-license",
            "MasterUsername": "noin_backend",
            "OptionGroupName": "default:mysql-5-6",
            "PercentProgress": 100,
            "Port": 3306,
            "ProcessorFeatures": [],
            "SnapshotCreateTime": "2019-08-06T12:30:34.515000+00:00",
            "SnapshotType": "manual",
            "Status": "available",
            "StorageType": "gp2",
            "VpcId": "vpc-b0eae7d4"
        },
        {
            "AllocatedStorage": 100,
            "AvailabilityZone": "ap-northeast-1c",
            "DBInstanceIdentifier": "noin-production-test001",
            "DBSnapshotArn": "arn:aws:rds:ap-northeast-1:416817624313:snapshot:noin-production-test001-final-snapshot",
            "DBSnapshotIdentifier": "noin-production-test001-final-snapshot",
            "DbiResourceId": "db-EXWXWB7N7P5YHB6BQJP44FWGA4",
            "Encrypted": true,
            "Engine": "mysql",
            "EngineVersion": "5.6.43",
            "IAMDatabaseAuthenticationEnabled": false,
            "InstanceCreateTime": "2019-06-18T06:24:50.850000+00:00",
            "KmsKeyId": "arn:aws:kms:ap-northeast-1:416817624313:key/f70c542e-295f-4e09-a995-c208de9af8e9",
            "LicenseModel": "general-public-license",
            "MasterUsername": "noin_backend",
            "OptionGroupName": "default:mysql-5-6",
            "PercentProgress": 100,
            "Port": 3306,
            "ProcessorFeatures": [],
            "SnapshotCreateTime": "2019-06-24T05:30:48.647000+00:00",
            "SnapshotType": "manual",
            "Status": "available",
            "StorageType": "gp2",
            "VpcId": "vpc-b0eae7d4"
        },
        {
            "AllocatedStorage": 100,
            "AvailabilityZone": "ap-northeast-1a",
            "DBInstanceIdentifier": "noin-staging-estest",
            "DBSnapshotArn": "arn:aws:rds:ap-northeast-1:416817624313:snapshot:noin-staging-estest-final-snapshot",
            "DBSnapshotIdentifier": "noin-staging-estest-final-snapshot",
            "DbiResourceId": "db-MJPQSGHC5CZLMFBOMXBC2ALHF4",
            "Encrypted": true,
            "Engine": "mysql",
            "EngineVersion": "5.6.35",
            "IAMDatabaseAuthenticationEnabled": false,
            "InstanceCreateTime": "2018-10-17T03:32:12.118000+00:00",
            "KmsKeyId": "arn:aws:kms:ap-northeast-1:416817624313:key/f70c542e-295f-4e09-a995-c208de9af8e9",
            "LicenseModel": "general-public-license",
            "MasterUsername": "noin_backend",
            "OptionGroupName": "default:mysql-5-6",
            "PercentProgress": 100,
            "Port": 3306,
            "ProcessorFeatures": [],
            "SnapshotCreateTime": "2018-10-23T08:10:26.090000+00:00",
            "SnapshotType": "manual",
            "Status": "available",
            "StorageType": "gp2",
            "VpcId": "vpc-4ec1e72a"
        },
        {
            "AllocatedStorage": 10,
            "AvailabilityZone": "ap-northeast-1c",
            "DBInstanceIdentifier": "nontv-staging",
            "DBSnapshotArn": "arn:aws:rds:ap-northeast-1:416817624313:snapshot:nontv-staging-2019-10-24-00-21",
            "DBSnapshotIdentifier": "nontv-staging-2019-10-24-00-21",
            "DbiResourceId": "db-EDNNVJ3GUXAU24KVMHMPE32SWQ",
            "Encrypted": false,
            "Engine": "mysql",
            "EngineVersion": "5.6.43",
            "IAMDatabaseAuthenticationEnabled": false,
            "InstanceCreateTime": "2017-09-03T23:44:18.416000+00:00",
            "LicenseModel": "general-public-license",
            "MasterUsername": "root",
            "OptionGroupName": "default:mysql-5-6",
            "PercentProgress": 100,
            "Port": 3306,
            "ProcessorFeatures": [],
            "SnapshotCreateTime": "2019-10-23T15:21:59.631000+00:00",
            "SnapshotType": "manual",
            "Status": "available",
            "StorageType": "gp2",
            "VpcId": "vpc-4ec1e72a"
        },
        {
            "AllocatedStorage": 10,
            "AvailabilityZone": "ap-northeast-1c",
            "DBInstanceIdentifier": "nontv-staging-rep-001",
            "DBSnapshotArn": "arn:aws:rds:ap-northeast-1:416817624313:snapshot:nontv-staging-rep-001-2019-10-24-00-33",
            "DBSnapshotIdentifier": "nontv-staging-rep-001-2019-10-24-00-33",
            "DbiResourceId": "db-F4JYX5IA7KNKQXAYNRGUM3TPCY",
            "Encrypted": false,
            "Engine": "mysql",
            "EngineVersion": "5.6.43",
            "IAMDatabaseAuthenticationEnabled": false,
            "InstanceCreateTime": "2019-07-02T01:55:15.207000+00:00",
            "LicenseModel": "general-public-license",
            "MasterUsername": "root",
            "OptionGroupName": "default:mysql-5-6",
            "PercentProgress": 100,
            "Port": 3306,
            "ProcessorFeatures": [],
            "SnapshotCreateTime": "2019-10-23T15:34:24.656000+00:00",
            "SnapshotType": "manual",
            "Status": "available",
            "StorageType": "gp2",
            "VpcId": "vpc-4ec1e72a"
        },
        {
            "AllocatedStorage": 10,
            "AvailabilityZone": "ap-northeast-1a",
            "DBInstanceIdentifier": "nontv-staging-sk2",
            "DBSnapshotArn": "arn:aws:rds:ap-northeast-1:416817624313:snapshot:nontv-staging-sk2-final-snapshot",
            "DBSnapshotIdentifier": "nontv-staging-sk2-final-snapshot",
            "DbiResourceId": "db-WHKP7BOK5TD3JMQWYO6R2SFRIM",
            "Encrypted": false,
            "Engine": "mysql",
            "EngineVersion": "5.6.40",
            "IAMDatabaseAuthenticationEnabled": false,
            "InstanceCreateTime": "2019-01-08T06:34:06.334000+00:00",
            "LicenseModel": "general-public-license",
            "MasterUsername": "root",
            "OptionGroupName": "default:mysql-5-6",
            "PercentProgress": 100,
            "Port": 3306,
            "ProcessorFeatures": [],
            "SnapshotCreateTime": "2019-07-07T17:07:00.597000+00:00",
            "SnapshotType": "manual",
            "Status": "available",
            "StorageType": "gp2",
            "VpcId": "vpc-4ec1e72a"
        },
        {
            "AllocatedStorage": 100,
            "AvailabilityZone": "ap-northeast-1a",
            "DBInstanceIdentifier": "production-recovery-tmp",
            "DBSnapshotArn": "arn:aws:rds:ap-northeast-1:416817624313:snapshot:production-recovery-tmp-final-snapshot",
            "DBSnapshotIdentifier": "production-recovery-tmp-final-snapshot",
            "DbiResourceId": "db-HPPNK53NSUXTVZWJO6CPZXIUSU",
            "Encrypted": true,
            "Engine": "mysql",
            "EngineVersion": "5.6.40",
            "IAMDatabaseAuthenticationEnabled": false,
            "InstanceCreateTime": "2019-06-01T07:22:35.634000+00:00",
            "KmsKeyId": "arn:aws:kms:ap-northeast-1:416817624313:key/f70c542e-295f-4e09-a995-c208de9af8e9",
            "LicenseModel": "general-public-license",
            "MasterUsername": "noin_backend",
            "OptionGroupName": "default:mysql-5-6",
            "PercentProgress": 100,
            "Port": 3306,
            "ProcessorFeatures": [],
            "SnapshotCreateTime": "2019-06-01T15:51:33.028000+00:00",
            "SnapshotType": "manual",
            "Status": "available",
            "StorageType": "gp2",
            "VpcId": "vpc-4ec1e72a"
        },
        {
            "AllocatedStorage": 50,
            "AvailabilityZone": "ap-northeast-1a",
            "DBInstanceIdentifier": "noin-corp-prod",
            "DBSnapshotArn": "arn:aws:rds:ap-northeast-1:416817624313:snapshot:rds:noin-corp-prod-2020-06-02-16-01",
            "DBSnapshotIdentifier": "rds:noin-corp-prod-2020-06-02-16-01",
            "DbiResourceId": "db-6DXQ6S624QC56AIZ4JHVZII5JQ",
            "Encrypted": true,
            "Engine": "mysql",
            "EngineVersion": "5.7.22",
            "IAMDatabaseAuthenticationEnabled": false,
            "InstanceCreateTime": "2019-06-04T15:00:18.557000+00:00",
            "KmsKeyId": "arn:aws:kms:ap-northeast-1:416817624313:key/f70c542e-295f-4e09-a995-c208de9af8e9",
            "LicenseModel": "general-public-license",
            "MasterUsername": "root",
            "OptionGroupName": "default:mysql-5-7",
            "PercentProgress": 100,
            "Port": 3306,
            "ProcessorFeatures": [],
            "SnapshotCreateTime": "2020-06-02T16:01:32.145000+00:00",
            "SnapshotType": "automated",
            "Status": "available",
            "StorageType": "gp2",
            "VpcId": "vpc-b0eae7d4"
        },
        {
            "AllocatedStorage": 50,
            "AvailabilityZone": "ap-northeast-1a",
            "DBInstanceIdentifier": "noin-corp-prod",
            "DBSnapshotArn": "arn:aws:rds:ap-northeast-1:416817624313:snapshot:rds:noin-corp-prod-2020-06-03-16-01",
            "DBSnapshotIdentifier": "rds:noin-corp-prod-2020-06-03-16-01",
            "DbiResourceId": "db-6DXQ6S624QC56AIZ4JHVZII5JQ",
            "Encrypted": true,
            "Engine": "mysql",
            "EngineVersion": "5.7.22",
            "IAMDatabaseAuthenticationEnabled": false,
            "InstanceCreateTime": "2019-06-04T15:00:18.557000+00:00",
            "KmsKeyId": "arn:aws:kms:ap-northeast-1:416817624313:key/f70c542e-295f-4e09-a995-c208de9af8e9",
            "LicenseModel": "general-public-license",
            "MasterUsername": "root",
            "OptionGroupName": "default:mysql-5-7",
            "PercentProgress": 100,
            "Port": 3306,
            "ProcessorFeatures": [],
            "SnapshotCreateTime": "2020-06-03T16:01:30.992000+00:00",
            "SnapshotType": "automated",
            "Status": "available",
            "StorageType": "gp2",
            "VpcId": "vpc-b0eae7d4"
        },
        {
            "AllocatedStorage": 50,
            "AvailabilityZone": "ap-northeast-1a",
            "DBInstanceIdentifier": "noin-corp-prod",
            "DBSnapshotArn": "arn:aws:rds:ap-northeast-1:416817624313:snapshot:rds:noin-corp-prod-2020-06-04-16-01",
            "DBSnapshotIdentifier": "rds:noin-corp-prod-2020-06-04-16-01",
            "DbiResourceId": "db-6DXQ6S624QC56AIZ4JHVZII5JQ",
            "Encrypted": true,
            "Engine": "mysql",
            "EngineVersion": "5.7.22",
            "IAMDatabaseAuthenticationEnabled": false,
            "InstanceCreateTime": "2019-06-04T15:00:18.557000+00:00",
            "KmsKeyId": "arn:aws:kms:ap-northeast-1:416817624313:key/f70c542e-295f-4e09-a995-c208de9af8e9",
            "LicenseModel": "general-public-license",
            "MasterUsername": "root",
            "OptionGroupName": "default:mysql-5-7",
            "PercentProgress": 100,
            "Port": 3306,
            "ProcessorFeatures": [],
            "SnapshotCreateTime": "2020-06-04T16:01:41.330000+00:00",
            "SnapshotType": "automated",
            "Status": "available",
            "StorageType": "gp2",
            "VpcId": "vpc-b0eae7d4"
        },
        {
            "AllocatedStorage": 50,
            "AvailabilityZone": "ap-northeast-1a",
            "DBInstanceIdentifier": "noin-corp-prod",
            "DBSnapshotArn": "arn:aws:rds:ap-northeast-1:416817624313:snapshot:rds:noin-corp-prod-2020-06-05-16-01",
            "DBSnapshotIdentifier": "rds:noin-corp-prod-2020-06-05-16-01",
            "DbiResourceId": "db-6DXQ6S624QC56AIZ4JHVZII5JQ",
            "Encrypted": true,
            "Engine": "mysql",
            "EngineVersion": "5.7.22",
            "IAMDatabaseAuthenticationEnabled": false,
            "InstanceCreateTime": "2019-06-04T15:00:18.557000+00:00",
            "KmsKeyId": "arn:aws:kms:ap-northeast-1:416817624313:key/f70c542e-295f-4e09-a995-c208de9af8e9",
            "LicenseModel": "general-public-license",
            "MasterUsername": "root",
            "OptionGroupName": "default:mysql-5-7",
            "PercentProgress": 100,
            "Port": 3306,
            "ProcessorFeatures": [],
            "SnapshotCreateTime": "2020-06-05T16:01:42.879000+00:00",
            "SnapshotType": "automated",
            "Status": "available",
            "StorageType": "gp2",
            "VpcId": "vpc-b0eae7d4"
        },
        {
            "AllocatedStorage": 50,
            "AvailabilityZone": "ap-northeast-1a",
            "DBInstanceIdentifier": "noin-corp-prod",
            "DBSnapshotArn": "arn:aws:rds:ap-northeast-1:416817624313:snapshot:rds:noin-corp-prod-2020-06-06-16-01",
            "DBSnapshotIdentifier": "rds:noin-corp-prod-2020-06-06-16-01",
            "DbiResourceId": "db-6DXQ6S624QC56AIZ4JHVZII5JQ",
            "Encrypted": true,
            "Engine": "mysql",
            "EngineVersion": "5.7.22",
            "IAMDatabaseAuthenticationEnabled": false,
            "InstanceCreateTime": "2019-06-04T15:00:18.557000+00:00",
            "KmsKeyId": "arn:aws:kms:ap-northeast-1:416817624313:key/f70c542e-295f-4e09-a995-c208de9af8e9",
            "LicenseModel": "general-public-license",
            "MasterUsername": "root",
            "OptionGroupName": "default:mysql-5-7",
            "PercentProgress": 100,
            "Port": 3306,
            "ProcessorFeatures": [],
            "SnapshotCreateTime": "2020-06-06T16:01:52.544000+00:00",
            "SnapshotType": "automated",
            "Status": "available",
            "StorageType": "gp2",
            "VpcId": "vpc-b0eae7d4"
        },
        {
            "AllocatedStorage": 50,
            "AvailabilityZone": "ap-northeast-1a",
            "DBInstanceIdentifier": "noin-corp-prod",
            "DBSnapshotArn": "arn:aws:rds:ap-northeast-1:416817624313:snapshot:rds:noin-corp-prod-2020-06-07-16-01",
            "DBSnapshotIdentifier": "rds:noin-corp-prod-2020-06-07-16-01",
            "DbiResourceId": "db-6DXQ6S624QC56AIZ4JHVZII5JQ",
            "Encrypted": true,
            "Engine": "mysql",
            "EngineVersion": "5.7.22",
            "IAMDatabaseAuthenticationEnabled": false,
            "InstanceCreateTime": "2019-06-04T15:00:18.557000+00:00",
            "KmsKeyId": "arn:aws:kms:ap-northeast-1:416817624313:key/f70c542e-295f-4e09-a995-c208de9af8e9",
            "LicenseModel": "general-public-license",
            "MasterUsername": "root",
            "OptionGroupName": "default:mysql-5-7",
            "PercentProgress": 100,
            "Port": 3306,
            "ProcessorFeatures": [],
            "SnapshotCreateTime": "2020-06-07T16:01:35.387000+00:00",
            "SnapshotType": "automated",
            "Status": "available",
            "StorageType": "gp2",
            "VpcId": "vpc-b0eae7d4"
        },
        {
            "AllocatedStorage": 50,
            "AvailabilityZone": "ap-northeast-1a",
            "DBInstanceIdentifier": "noin-corp-prod",
            "DBSnapshotArn": "arn:aws:rds:ap-northeast-1:416817624313:snapshot:rds:noin-corp-prod-2020-06-08-16-01",
            "DBSnapshotIdentifier": "rds:noin-corp-prod-2020-06-08-16-01",
            "DbiResourceId": "db-6DXQ6S624QC56AIZ4JHVZII5JQ",
            "Encrypted": true,
            "Engine": "mysql",
            "EngineVersion": "5.7.22",
            "IAMDatabaseAuthenticationEnabled": false,
            "InstanceCreateTime": "2019-06-04T15:00:18.557000+00:00",
            "KmsKeyId": "arn:aws:kms:ap-northeast-1:416817624313:key/f70c542e-295f-4e09-a995-c208de9af8e9",
            "LicenseModel": "general-public-license",
            "MasterUsername": "root",
            "OptionGroupName": "default:mysql-5-7",
            "PercentProgress": 100,
            "Port": 3306,
            "ProcessorFeatures": [],
            "SnapshotCreateTime": "2020-06-08T16:01:41.491000+00:00",
            "SnapshotType": "automated",
            "Status": "available",
            "StorageType": "gp2",
            "VpcId": "vpc-b0eae7d4"
        },
        {
            "AllocatedStorage": 50,
            "AvailabilityZone": "ap-northeast-1a",
            "DBInstanceIdentifier": "noin-corp-prod",
            "DBSnapshotArn": "arn:aws:rds:ap-northeast-1:416817624313:snapshot:rds:noin-corp-prod-2020-06-09-16-01",
            "DBSnapshotIdentifier": "rds:noin-corp-prod-2020-06-09-16-01",
            "DbiResourceId": "db-6DXQ6S624QC56AIZ4JHVZII5JQ",
            "Encrypted": true,
            "Engine": "mysql",
            "EngineVersion": "5.7.22",
            "IAMDatabaseAuthenticationEnabled": false,
            "InstanceCreateTime": "2019-06-04T15:00:18.557000+00:00",
            "KmsKeyId": "arn:aws:kms:ap-northeast-1:416817624313:key/f70c542e-295f-4e09-a995-c208de9af8e9",
            "LicenseModel": "general-public-license",
            "MasterUsername": "root",
            "OptionGroupName": "default:mysql-5-7",
            "PercentProgress": 100,
            "Port": 3306,
            "ProcessorFeatures": [],
            "SnapshotCreateTime": "2020-06-09T16:02:04.186000+00:00",
            "SnapshotType": "automated",
            "Status": "available",
            "StorageType": "gp2",
            "VpcId": "vpc-b0eae7d4"
        },
        {
            "AllocatedStorage": 100,
            "AvailabilityZone": "ap-northeast-1c",
            "DBInstanceIdentifier": "noin-production",
            "DBSnapshotArn": "arn:aws:rds:ap-northeast-1:416817624313:snapshot:rds:noin-production-2020-05-26-18-07",
            "DBSnapshotIdentifier": "rds:noin-production-2020-05-26-18-07",
            "DbiResourceId": "db-ONZWTN7HWO2DX26K2OZNB7VMC4",
            "Encrypted": true,
            "Engine": "mysql",
            "EngineVersion": "5.6.43",
            "IAMDatabaseAuthenticationEnabled": false,
            "InstanceCreateTime": "2019-06-16T21:54:51.778000+00:00",
            "KmsKeyId": "arn:aws:kms:ap-northeast-1:416817624313:key/f70c542e-295f-4e09-a995-c208de9af8e9",
            "LicenseModel": "general-public-license",
            "MasterUsername": "noin_backend",
            "OptionGroupName": "default:mysql-5-6",
            "PercentProgress": 100,
            "Port": 3306,
            "ProcessorFeatures": [],
            "SnapshotCreateTime": "2020-05-26T18:08:25.910000+00:00",
            "SnapshotType": "automated",
            "Status": "available",
            "StorageType": "gp2",
            "VpcId": "vpc-b0eae7d4"
        },
        {
            "AllocatedStorage": 100,
            "AvailabilityZone": "ap-northeast-1c",
            "DBInstanceIdentifier": "noin-production",
            "DBSnapshotArn": "arn:aws:rds:ap-northeast-1:416817624313:snapshot:rds:noin-production-2020-05-27-18-07",
            "DBSnapshotIdentifier": "rds:noin-production-2020-05-27-18-07",
            "DbiResourceId": "db-ONZWTN7HWO2DX26K2OZNB7VMC4",
            "Encrypted": true,
            "Engine": "mysql",
            "EngineVersion": "5.6.43",
            "IAMDatabaseAuthenticationEnabled": false,
            "InstanceCreateTime": "2019-06-16T21:54:51.778000+00:00",
            "KmsKeyId": "arn:aws:kms:ap-northeast-1:416817624313:key/f70c542e-295f-4e09-a995-c208de9af8e9",
            "LicenseModel": "general-public-license",
            "MasterUsername": "noin_backend",
            "OptionGroupName": "default:mysql-5-6",
            "PercentProgress": 100,
            "Port": 3306,
            "ProcessorFeatures": [],
            "SnapshotCreateTime": "2020-05-27T18:07:43.248000+00:00",
            "SnapshotType": "automated",
            "Status": "available",
            "StorageType": "gp2",
            "VpcId": "vpc-b0eae7d4"
        },
        {
            "AllocatedStorage": 100,
            "AvailabilityZone": "ap-northeast-1c",
            "DBInstanceIdentifier": "noin-production",
            "DBSnapshotArn": "arn:aws:rds:ap-northeast-1:416817624313:snapshot:rds:noin-production-2020-05-28-18-07",
            "DBSnapshotIdentifier": "rds:noin-production-2020-05-28-18-07",
            "DbiResourceId": "db-ONZWTN7HWO2DX26K2OZNB7VMC4",
            "Encrypted": true,
            "Engine": "mysql",
            "EngineVersion": "5.6.43",
            "IAMDatabaseAuthenticationEnabled": false,
            "InstanceCreateTime": "2019-06-16T21:54:51.778000+00:00",
            "KmsKeyId": "arn:aws:kms:ap-northeast-1:416817624313:key/f70c542e-295f-4e09-a995-c208de9af8e9",
            "LicenseModel": "general-public-license",
            "MasterUsername": "noin_backend",
            "OptionGroupName": "default:mysql-5-6",
            "PercentProgress": 100,
            "Port": 3306,
            "ProcessorFeatures": [],
            "SnapshotCreateTime": "2020-05-28T18:07:45.371000+00:00",
            "SnapshotType": "automated",
            "Status": "available",
            "StorageType": "gp2",
            "VpcId": "vpc-b0eae7d4"
        },
        {
            "AllocatedStorage": 100,
            "AvailabilityZone": "ap-northeast-1c",
            "DBInstanceIdentifier": "noin-production",
            "DBSnapshotArn": "arn:aws:rds:ap-northeast-1:416817624313:snapshot:rds:noin-production-2020-05-29-18-07",
            "DBSnapshotIdentifier": "rds:noin-production-2020-05-29-18-07",
            "DbiResourceId": "db-ONZWTN7HWO2DX26K2OZNB7VMC4",
            "Encrypted": true,
            "Engine": "mysql",
            "EngineVersion": "5.6.43",
            "IAMDatabaseAuthenticationEnabled": false,
            "InstanceCreateTime": "2019-06-16T21:54:51.778000+00:00",
            "KmsKeyId": "arn:aws:kms:ap-northeast-1:416817624313:key/f70c542e-295f-4e09-a995-c208de9af8e9",
            "LicenseModel": "general-public-license",
            "MasterUsername": "noin_backend",
            "OptionGroupName": "default:mysql-5-6",
            "PercentProgress": 100,
            "Port": 3306,
            "ProcessorFeatures": [],
            "SnapshotCreateTime": "2020-05-29T18:08:12.106000+00:00",
            "SnapshotType": "automated",
            "Status": "available",
            "StorageType": "gp2",
            "VpcId": "vpc-b0eae7d4"
        },
        {
            "AllocatedStorage": 100,
            "AvailabilityZone": "ap-northeast-1c",
            "DBInstanceIdentifier": "noin-production",
            "DBSnapshotArn": "arn:aws:rds:ap-northeast-1:416817624313:snapshot:rds:noin-production-2020-05-30-18-07",
            "DBSnapshotIdentifier": "rds:noin-production-2020-05-30-18-07",
            "DbiResourceId": "db-ONZWTN7HWO2DX26K2OZNB7VMC4",
            "Encrypted": true,
            "Engine": "mysql",
            "EngineVersion": "5.6.43",
            "IAMDatabaseAuthenticationEnabled": false,
            "InstanceCreateTime": "2019-06-16T21:54:51.778000+00:00",
            "KmsKeyId": "arn:aws:kms:ap-northeast-1:416817624313:key/f70c542e-295f-4e09-a995-c208de9af8e9",
            "LicenseModel": "general-public-license",
            "MasterUsername": "noin_backend",
            "OptionGroupName": "default:mysql-5-6",
            "PercentProgress": 100,
            "Port": 3306,
            "ProcessorFeatures": [],
            "SnapshotCreateTime": "2020-05-30T18:08:15.998000+00:00",
            "SnapshotType": "automated",
            "Status": "available",
            "StorageType": "gp2",
            "VpcId": "vpc-b0eae7d4"
        },
        {
            "AllocatedStorage": 100,
            "AvailabilityZone": "ap-northeast-1c",
            "DBInstanceIdentifier": "noin-production",
            "DBSnapshotArn": "arn:aws:rds:ap-northeast-1:416817624313:snapshot:rds:noin-production-2020-05-31-18-07",
            "DBSnapshotIdentifier": "rds:noin-production-2020-05-31-18-07",
            "DbiResourceId": "db-ONZWTN7HWO2DX26K2OZNB7VMC4",
            "Encrypted": true,
            "Engine": "mysql",
            "EngineVersion": "5.6.43",
            "IAMDatabaseAuthenticationEnabled": false,
            "InstanceCreateTime": "2019-06-16T21:54:51.778000+00:00",
            "KmsKeyId": "arn:aws:kms:ap-northeast-1:416817624313:key/f70c542e-295f-4e09-a995-c208de9af8e9",
            "LicenseModel": "general-public-license",
            "MasterUsername": "noin_backend",
            "OptionGroupName": "default:mysql-5-6",
            "PercentProgress": 100,
            "Port": 3306,
            "ProcessorFeatures": [],
            "SnapshotCreateTime": "2020-05-31T18:07:42.153000+00:00",
            "SnapshotType": "automated",
            "Status": "available",
            "StorageType": "gp2",
            "VpcId": "vpc-b0eae7d4"
        },
        {
            "AllocatedStorage": 100,
            "AvailabilityZone": "ap-northeast-1c",
            "DBInstanceIdentifier": "noin-production",
            "DBSnapshotArn": "arn:aws:rds:ap-northeast-1:416817624313:snapshot:rds:noin-production-2020-06-01-18-08",
            "DBSnapshotIdentifier": "rds:noin-production-2020-06-01-18-08",
            "DbiResourceId": "db-ONZWTN7HWO2DX26K2OZNB7VMC4",
            "Encrypted": true,
            "Engine": "mysql",
            "EngineVersion": "5.6.43",
            "IAMDatabaseAuthenticationEnabled": false,
            "InstanceCreateTime": "2019-06-16T21:54:51.778000+00:00",
            "KmsKeyId": "arn:aws:kms:ap-northeast-1:416817624313:key/f70c542e-295f-4e09-a995-c208de9af8e9",
            "LicenseModel": "general-public-license",
            "MasterUsername": "noin_backend",
            "OptionGroupName": "default:mysql-5-6",
            "PercentProgress": 100,
            "Port": 3306,
            "ProcessorFeatures": [],
            "SnapshotCreateTime": "2020-06-01T18:08:36.768000+00:00",
            "SnapshotType": "automated",
            "Status": "available",
            "StorageType": "gp2",
            "VpcId": "vpc-b0eae7d4"
        },
        {
            "AllocatedStorage": 100,
            "AvailabilityZone": "ap-northeast-1c",
            "DBInstanceIdentifier": "noin-production",
            "DBSnapshotArn": "arn:aws:rds:ap-northeast-1:416817624313:snapshot:rds:noin-production-2020-06-02-18-08",
            "DBSnapshotIdentifier": "rds:noin-production-2020-06-02-18-08",
            "DbiResourceId": "db-ONZWTN7HWO2DX26K2OZNB7VMC4",
            "Encrypted": true,
            "Engine": "mysql",
            "EngineVersion": "5.6.43",
            "IAMDatabaseAuthenticationEnabled": false,
            "InstanceCreateTime": "2019-06-16T21:54:51.778000+00:00",
            "KmsKeyId": "arn:aws:kms:ap-northeast-1:416817624313:key/f70c542e-295f-4e09-a995-c208de9af8e9",
            "LicenseModel": "general-public-license",
            "MasterUsername": "noin_backend",
            "OptionGroupName": "default:mysql-5-6",
            "PercentProgress": 100,
            "Port": 3306,
            "ProcessorFeatures": [],
            "SnapshotCreateTime": "2020-06-02T18:08:21.452000+00:00",
            "SnapshotType": "automated",
            "Status": "available",
            "StorageType": "gp2",
            "VpcId": "vpc-b0eae7d4"
        },
        {
            "AllocatedStorage": 100,
            "AvailabilityZone": "ap-northeast-1c",
            "DBInstanceIdentifier": "noin-production",
            "DBSnapshotArn": "arn:aws:rds:ap-northeast-1:416817624313:snapshot:rds:noin-production-2020-06-03-18-07",
            "DBSnapshotIdentifier": "rds:noin-production-2020-06-03-18-07",
            "DbiResourceId": "db-ONZWTN7HWO2DX26K2OZNB7VMC4",
            "Encrypted": true,
            "Engine": "mysql",
            "EngineVersion": "5.6.43",
            "IAMDatabaseAuthenticationEnabled": false,
            "InstanceCreateTime": "2019-06-16T21:54:51.778000+00:00",
            "KmsKeyId": "arn:aws:kms:ap-northeast-1:416817624313:key/f70c542e-295f-4e09-a995-c208de9af8e9",
            "LicenseModel": "general-public-license",
            "MasterUsername": "noin_backend",
            "OptionGroupName": "default:mysql-5-6",
            "PercentProgress": 100,
            "Port": 3306,
            "ProcessorFeatures": [],
            "SnapshotCreateTime": "2020-06-03T18:08:20.491000+00:00",
            "SnapshotType": "automated",
            "Status": "available",
            "StorageType": "gp2",
            "VpcId": "vpc-b0eae7d4"
        },
        {
            "AllocatedStorage": 100,
            "AvailabilityZone": "ap-northeast-1c",
            "DBInstanceIdentifier": "noin-production",
            "DBSnapshotArn": "arn:aws:rds:ap-northeast-1:416817624313:snapshot:rds:noin-production-2020-06-04-18-08",
            "DBSnapshotIdentifier": "rds:noin-production-2020-06-04-18-08",
            "DbiResourceId": "db-ONZWTN7HWO2DX26K2OZNB7VMC4",
            "Encrypted": true,
            "Engine": "mysql",
            "EngineVersion": "5.6.43",
            "IAMDatabaseAuthenticationEnabled": false,
            "InstanceCreateTime": "2019-06-16T21:54:51.778000+00:00",
            "KmsKeyId": "arn:aws:kms:ap-northeast-1:416817624313:key/f70c542e-295f-4e09-a995-c208de9af8e9",
            "LicenseModel": "general-public-license",
            "MasterUsername": "noin_backend",
            "OptionGroupName": "default:mysql-5-6",
            "PercentProgress": 100,
            "Port": 3306,
            "ProcessorFeatures": [],
            "SnapshotCreateTime": "2020-06-04T18:08:23.047000+00:00",
            "SnapshotType": "automated",
            "Status": "available",
            "StorageType": "gp2",
            "VpcId": "vpc-b0eae7d4"
        },
        {
            "AllocatedStorage": 100,
            "AvailabilityZone": "ap-northeast-1c",
            "DBInstanceIdentifier": "noin-production",
            "DBSnapshotArn": "arn:aws:rds:ap-northeast-1:416817624313:snapshot:rds:noin-production-2020-06-05-18-08",
            "DBSnapshotIdentifier": "rds:noin-production-2020-06-05-18-08",
            "DbiResourceId": "db-ONZWTN7HWO2DX26K2OZNB7VMC4",
            "Encrypted": true,
            "Engine": "mysql",
            "EngineVersion": "5.6.43",
            "IAMDatabaseAuthenticationEnabled": false,
            "InstanceCreateTime": "2019-06-16T21:54:51.778000+00:00",
            "KmsKeyId": "arn:aws:kms:ap-northeast-1:416817624313:key/f70c542e-295f-4e09-a995-c208de9af8e9",
            "LicenseModel": "general-public-license",
            "MasterUsername": "noin_backend",
            "OptionGroupName": "default:mysql-5-6",
            "PercentProgress": 100,
            "Port": 3306,
            "ProcessorFeatures": [],
            "SnapshotCreateTime": "2020-06-05T18:08:42.973000+00:00",
            "SnapshotType": "automated",
            "Status": "available",
            "StorageType": "gp2",
            "VpcId": "vpc-b0eae7d4"
        },
        {
            "AllocatedStorage": 100,
            "AvailabilityZone": "ap-northeast-1c",
            "DBInstanceIdentifier": "noin-production",
            "DBSnapshotArn": "arn:aws:rds:ap-northeast-1:416817624313:snapshot:rds:noin-production-2020-06-06-18-07",
            "DBSnapshotIdentifier": "rds:noin-production-2020-06-06-18-07",
            "DbiResourceId": "db-ONZWTN7HWO2DX26K2OZNB7VMC4",
            "Encrypted": true,
            "Engine": "mysql",
            "EngineVersion": "5.6.43",
            "IAMDatabaseAuthenticationEnabled": false,
            "InstanceCreateTime": "2019-06-16T21:54:51.778000+00:00",
            "KmsKeyId": "arn:aws:kms:ap-northeast-1:416817624313:key/f70c542e-295f-4e09-a995-c208de9af8e9",
            "LicenseModel": "general-public-license",
            "MasterUsername": "noin_backend",
            "OptionGroupName": "default:mysql-5-6",
            "PercentProgress": 100,
            "Port": 3306,
            "ProcessorFeatures": [],
            "SnapshotCreateTime": "2020-06-06T18:07:41.888000+00:00",
            "SnapshotType": "automated",
            "Status": "available",
            "StorageType": "gp2",
            "VpcId": "vpc-b0eae7d4"
        },
        {
            "AllocatedStorage": 100,
            "AvailabilityZone": "ap-northeast-1c",
            "DBInstanceIdentifier": "noin-production",
            "DBSnapshotArn": "arn:aws:rds:ap-northeast-1:416817624313:snapshot:rds:noin-production-2020-06-07-18-07",
            "DBSnapshotIdentifier": "rds:noin-production-2020-06-07-18-07",
            "DbiResourceId": "db-ONZWTN7HWO2DX26K2OZNB7VMC4",
            "Encrypted": true,
            "Engine": "mysql",
            "EngineVersion": "5.6.43",
            "IAMDatabaseAuthenticationEnabled": false,
            "InstanceCreateTime": "2019-06-16T21:54:51.778000+00:00",
            "KmsKeyId": "arn:aws:kms:ap-northeast-1:416817624313:key/f70c542e-295f-4e09-a995-c208de9af8e9",
            "LicenseModel": "general-public-license",
            "MasterUsername": "noin_backend",
            "OptionGroupName": "default:mysql-5-6",
            "PercentProgress": 100,
            "Port": 3306,
            "ProcessorFeatures": [],
            "SnapshotCreateTime": "2020-06-07T18:08:16.587000+00:00",
            "SnapshotType": "automated",
            "Status": "available",
            "StorageType": "gp2",
            "VpcId": "vpc-b0eae7d4"
        },
        {
            "AllocatedStorage": 100,
            "AvailabilityZone": "ap-northeast-1c",
            "DBInstanceIdentifier": "noin-production",
            "DBSnapshotArn": "arn:aws:rds:ap-northeast-1:416817624313:snapshot:rds:noin-production-2020-06-08-18-08",
            "DBSnapshotIdentifier": "rds:noin-production-2020-06-08-18-08",
            "DbiResourceId": "db-ONZWTN7HWO2DX26K2OZNB7VMC4",
            "Encrypted": true,
            "Engine": "mysql",
            "EngineVersion": "5.6.43",
            "IAMDatabaseAuthenticationEnabled": false,
            "InstanceCreateTime": "2019-06-16T21:54:51.778000+00:00",
            "KmsKeyId": "arn:aws:kms:ap-northeast-1:416817624313:key/f70c542e-295f-4e09-a995-c208de9af8e9",
            "LicenseModel": "general-public-license",
            "MasterUsername": "noin_backend",
            "OptionGroupName": "default:mysql-5-6",
            "PercentProgress": 100,
            "Port": 3306,
            "ProcessorFeatures": [],
            "SnapshotCreateTime": "2020-06-08T18:08:33.948000+00:00",
            "SnapshotType": "automated",
            "Status": "available",
            "StorageType": "gp2",
            "VpcId": "vpc-b0eae7d4"
        },
        {
            "AllocatedStorage": 100,
            "AvailabilityZone": "ap-northeast-1c",
            "DBInstanceIdentifier": "noin-production",
            "DBSnapshotArn": "arn:aws:rds:ap-northeast-1:416817624313:snapshot:rds:noin-production-2020-06-09-18-08",
            "DBSnapshotIdentifier": "rds:noin-production-2020-06-09-18-08",
            "DbiResourceId": "db-ONZWTN7HWO2DX26K2OZNB7VMC4",
            "Encrypted": true,
            "Engine": "mysql",
            "EngineVersion": "5.6.43",
            "IAMDatabaseAuthenticationEnabled": false,
            "InstanceCreateTime": "2019-06-16T21:54:51.778000+00:00",
            "KmsKeyId": "arn:aws:kms:ap-northeast-1:416817624313:key/f70c542e-295f-4e09-a995-c208de9af8e9",
            "LicenseModel": "general-public-license",
            "MasterUsername": "noin_backend",
            "OptionGroupName": "default:mysql-5-6",
            "PercentProgress": 100,
            "Port": 3306,
            "ProcessorFeatures": [],
            "SnapshotCreateTime": "2020-06-09T18:08:23.857000+00:00",
            "SnapshotType": "automated",
            "Status": "available",
            "StorageType": "gp2",
            "VpcId": "vpc-b0eae7d4"
        },
        {
            "AllocatedStorage": 10,
            "AvailabilityZone": "ap-northeast-1c",
            "DBInstanceIdentifier": "nontv-staging",
            "DBSnapshotArn": "arn:aws:rds:ap-northeast-1:416817624313:snapshot:rds:nontv-staging-2020-06-06-15-07",
            "DBSnapshotIdentifier": "rds:nontv-staging-2020-06-06-15-07",
            "DbiResourceId": "db-EDNNVJ3GUXAU24KVMHMPE32SWQ",
            "Encrypted": false,
            "Engine": "mysql",
            "EngineVersion": "5.6.43",
            "IAMDatabaseAuthenticationEnabled": false,
            "InstanceCreateTime": "2017-09-03T23:44:18.416000+00:00",
            "LicenseModel": "general-public-license",
            "MasterUsername": "root",
            "OptionGroupName": "default:mysql-5-6",
            "PercentProgress": 100,
            "Port": 3306,
            "ProcessorFeatures": [],
            "SnapshotCreateTime": "2020-06-06T15:07:41.711000+00:00",
            "SnapshotType": "automated",
            "Status": "available",
            "StorageType": "gp2",
            "VpcId": "vpc-4ec1e72a"
        },
        {
            "AllocatedStorage": 10,
            "AvailabilityZone": "ap-northeast-1c",
            "DBInstanceIdentifier": "nontv-staging",
            "DBSnapshotArn": "arn:aws:rds:ap-northeast-1:416817624313:snapshot:rds:nontv-staging-2020-06-07-15-07",
            "DBSnapshotIdentifier": "rds:nontv-staging-2020-06-07-15-07",
            "DbiResourceId": "db-EDNNVJ3GUXAU24KVMHMPE32SWQ",
            "Encrypted": false,
            "Engine": "mysql",
            "EngineVersion": "5.6.43",
            "IAMDatabaseAuthenticationEnabled": false,
            "InstanceCreateTime": "2017-09-03T23:44:18.416000+00:00",
            "LicenseModel": "general-public-license",
            "MasterUsername": "root",
            "OptionGroupName": "default:mysql-5-6",
            "PercentProgress": 100,
            "Port": 3306,
            "ProcessorFeatures": [],
            "SnapshotCreateTime": "2020-06-07T15:07:29.568000+00:00",
            "SnapshotType": "automated",
            "Status": "available",
            "StorageType": "gp2",
            "VpcId": "vpc-4ec1e72a"
        },
        {
            "AllocatedStorage": 10,
            "AvailabilityZone": "ap-northeast-1c",
            "DBInstanceIdentifier": "nontv-staging",
            "DBSnapshotArn": "arn:aws:rds:ap-northeast-1:416817624313:snapshot:rds:nontv-staging-2020-06-08-15-07",
            "DBSnapshotIdentifier": "rds:nontv-staging-2020-06-08-15-07",
            "DbiResourceId": "db-EDNNVJ3GUXAU24KVMHMPE32SWQ",
            "Encrypted": false,
            "Engine": "mysql",
            "EngineVersion": "5.6.43",
            "IAMDatabaseAuthenticationEnabled": false,
            "InstanceCreateTime": "2017-09-03T23:44:18.416000+00:00",
            "LicenseModel": "general-public-license",
            "MasterUsername": "root",
            "OptionGroupName": "default:mysql-5-6",
            "PercentProgress": 100,
            "Port": 3306,
            "ProcessorFeatures": [],
            "SnapshotCreateTime": "2020-06-08T15:07:44.919000+00:00",
            "SnapshotType": "automated",
            "Status": "available",
            "StorageType": "gp2",
            "VpcId": "vpc-4ec1e72a"
        },
        {
            "AllocatedStorage": 10,
            "AvailabilityZone": "ap-northeast-1c",
            "DBInstanceIdentifier": "nontv-staging",
            "DBSnapshotArn": "arn:aws:rds:ap-northeast-1:416817624313:snapshot:rds:nontv-staging-2020-06-09-15-07",
            "DBSnapshotIdentifier": "rds:nontv-staging-2020-06-09-15-07",
            "DbiResourceId": "db-EDNNVJ3GUXAU24KVMHMPE32SWQ",
            "Encrypted": false,
            "Engine": "mysql",
            "EngineVersion": "5.6.43",
            "IAMDatabaseAuthenticationEnabled": false,
            "InstanceCreateTime": "2017-09-03T23:44:18.416000+00:00",
            "LicenseModel": "general-public-license",
            "MasterUsername": "root",
            "OptionGroupName": "default:mysql-5-6",
            "PercentProgress": 100,
            "Port": 3306,
            "ProcessorFeatures": [],
            "SnapshotCreateTime": "2020-06-09T15:08:14.572000+00:00",
            "SnapshotType": "automated",
            "Status": "available",
            "StorageType": "gp2",
            "VpcId": "vpc-4ec1e72a"
        },
        {
            "AllocatedStorage": 100,
            "AvailabilityZone": "ap-northeast-1c",
            "DBInstanceIdentifier": "noin-production",
            "DBSnapshotArn": "arn:aws:rds:ap-northeast-1:416817624313:snapshot:snapshot-for-brand-unified-operation-20200117",
            "DBSnapshotIdentifier": "snapshot-for-brand-unified-operation-20200117",
            "DbiResourceId": "db-ONZWTN7HWO2DX26K2OZNB7VMC4",
            "Encrypted": true,
            "Engine": "mysql",
            "EngineVersion": "5.6.43",
            "IAMDatabaseAuthenticationEnabled": false,
            "InstanceCreateTime": "2019-06-16T21:54:51.778000+00:00",
            "KmsKeyId": "arn:aws:kms:ap-northeast-1:416817624313:key/f70c542e-295f-4e09-a995-c208de9af8e9",
            "LicenseModel": "general-public-license",
            "MasterUsername": "noin_backend",
            "OptionGroupName": "default:mysql-5-6",
            "PercentProgress": 100,
            "Port": 3306,
            "ProcessorFeatures": [],
            "SnapshotCreateTime": "2020-01-17T04:39:38.860000+00:00",
            "SnapshotType": "manual",
            "Status": "available",
            "StorageType": "gp2",
            "VpcId": "vpc-b0eae7d4"
        }
    ]
}